aiagent_runner/__init__.py
aiagent_runner/__main__.py
aiagent_runner/config.py
aiagent_runner/cooldown.py
aiagent_runner/coordinator.py
aiagent_runner/coordinator_config.py
aiagent_runner/executor.py
aiagent_runner/lock.py
aiagent_runner/log_uploader.py
aiagent_runner/mcp_client.py
aiagent_runner/models.py
aiagent_runner/platform.py
aiagent_runner/prompt_builder.py
aiagent_runner/quota_detector.py
aiagent_runner/runner.py
aiagent_runner-0.1.13.dist-info/METADATA
aiagent_runner-0.1.13.dist-info/WHEEL
aiagent_runner-0.1.13.dist-info/entry_points.txt
aiagent_runner-0.1.13.dist-info/RECORD
