Metadata-Version: 2.4
Name: aiagent-runner
Version: 0.1.13
Summary: Runner for AI Agent PM - executes tasks via MCP and CLI
Author: AI Agent PM Team
License-Expression: MIT
Keywords: agent,ai,automation,mcp,orchestration,task-management
Classifier: Development Status :: 3 - Alpha
Classifier: Environment :: Console
Classifier: Intended Audience :: Developers
Classifier: License :: OSI Approved :: MIT License
Classifier: Operating System :: OS Independent
Classifier: Programming Language :: Python :: 3
Classifier: Programming Language :: Python :: 3.11
Classifier: Programming Language :: Python :: 3.12
Classifier: Topic :: Software Development :: Libraries :: Python Modules
Requires-Python: >=3.9
Requires-Dist: filelock>=3.0.0
Requires-Dist: pyyaml>=6.0
Provides-Extra: dev
Requires-Dist: aiohttp>=3.9; extra == 'dev'
Requires-Dist: pytest-asyncio>=0.23; extra == 'dev'
Requires-Dist: pytest-cov>=4.1; extra == 'dev'
Requires-Dist: pytest>=8.0; extra == 'dev'
Provides-Extra: http
Requires-Dist: aiohttp>=3.9; extra == 'http'
